graphcode/__init__.py
graphcode/cipher.py
graphcode/conditions.py
graphcode/conf.py
graphcode/credentials.py
graphcode/csv.py
graphcode/delimiter.py
graphcode/io.py
graphcode/json.py
graphcode/ldap.py
graphcode/lib.py
graphcode/logging.py
graphcode/parse.py
graphcode/path.py
graphcode/unittest.py
graphcode/aws/__init__.py
graphcode/aws/arguments.py
graphcode/aws/athena.py
graphcode/aws/names.py
graphcode/aws/parse.py
graphcode/aws/pricing.py
graphcode/aws/s3.py
graphcode/aws/sqs.py
graphcode/email/__init__.py
graphcode/email/expiredCookieEmail.py
graphcode/email/processedEmail.py
graphcode/email/testEmail.py
graphcode/email/welcomeEmail.py
graphcode/email/welcomeIdEmail.py
graphcode/itemDB/__init__.py
graphcode/itemDB/deleteItem.py
graphcode/itemDB/getItem.py
graphcode/itemDB/putItem.py
graphcode/workbench/__init__.py
graphcode/workbench/getWbResultsToList.py
graphcode/workbench/k2WorkbenchApiListsToGetTaRecommendations.py
pado/__init__.py
pado/auth.py
pado/chart.py
pado/chartV2.py
pado/conf.py
pado/flask.py
pado/form.py
pado/render.py
pado/response.py
pado/rules.py
pado/templates.py
pado/theme/__init__.py
pado/theme/default.py
pathway/__init__.py
pathway/inputs.py
tammy/__init__.py
tammy/lib.py
tammy/wbTemplate.py
tammy/api/__init__.py
tammy/api/iam/__init__.py
tammy/api/iam/discoverPolicies/__init__.py
tammy/awsdw/__init__.py
tammy/awsdw/templates.py
tammy/campaign/__init__.py
tammy/campaign/deleteCampaigns/__init__.py
tammy/campaign/describeCampaignNames/__init__.py
tammy/campaign/describeCampaigns/__init__.py
tammy/campaign/describeTemplate/__init__.py
tammy/campaign/discoverCampaigns/__init__.py
tammy/campaign/discoverCampaigns/IPv4_Awareness/__init__.py
tammy/campaign/discoverCampaigns/NATGW_Optimization/__init__.py
tammy/cmApi/__init__.py
tammy/cmApi/getDante/__init__.py
tammy/cmApi/getDante/K2-ec2_contributionmodelasset_Dante-curated-ec2/__init__.py
tammy/cmApi/getDante/K2-service-quotas_contributionmodelasset_K2-service-quotas/__init__.py
graphcode-0.1.4.16.dist-info/LICENSE
graphcode-0.1.4.16.dist-info/METADATA
graphcode-0.1.4.16.dist-info/WHEEL
graphcode-0.1.4.16.dist-info/top_level.txt
graphcode-0.1.4.16.dist-info/RECORD
