Metadata-Version: 2.1
Name: graphcode
Version: 0.1.4.16
Summary: graphcode
Home-page: https://github.com/tammysdk/graphcode
Author: Ryeojin Moon
Author-email: ryeojin@gmail.com
License: MIT
Requires-Python: >=3.8
License-File: LICENSE
